[
    {
        "id": 1,
        "HP": 200,
        "KW": 149.14,
        "torque": 250,
        "evHP": 100,
        "evKW": 74.57,
        "evTorque": 120,
        "acceleration": 7.5,
        "vehicleTopSpeed": 180,
        "engineCapacity": 2000,
        "modelYear": 2022,
        "hasTractionEnabled": true,
        "hasImmobilizer": true,
        "hasTheftDetection": false,
        "currentMileageDynamic": 15000,
        "yearlyMilageDynamic": 20000,
        "highwayYearlyMilageDynamic": 12000,
        "dailyMilageDynamic": 50,
        "serviceHistory": 2,
        "serviceDue": 30000,
        "timeToService": 500,
        "recallHistory": 1,
        "tractionControlEngaged": true,
        "accelerationLongitudinal": 0.8,
        "accelerationLateral": 0.2,
        "accelerationVertical": 0.1,
        "brakingFrequency": 300,
        "brakePedalForce": 120,
        "brakePedalSpeed": 0.5,
        "performanceMode": 1,
        "emergencyBraking": 0.3,
        "engnitionOn": true,
        "engnitionOff": false,
        "ignitionOnTime": 120,
        "ignitionOffTime": 30,
        "logitude": 34.0522,
        "latitude": -118.2437,
        "altitude": 150,
        "heading": 45,
        "isMoving": true,
        "hornIsActive": false,
        "drivingSpeed": 60,
        "wheelSpin": 0.5,
        "decelrationRate": 2.5,
        "steeringSpeedTurn": 0.1,
        "laneDepartureWarnning": 0.2,
        "adasAbsIsActive": true,
        "obstacleDetectionIsActive": false,
        "driverIntervention": false,
        "obstacleDetectionWarning": null,
        "speedSet": 65,
        "yaw": 10,
        "pitch": 5,
        "roll": 0.5,
        "gForce": 0.8,
        "trailerIncluded": false,
        "row1Pos1Isbelted": true,
        "row1Pos2Isbelted": false,
        "row2Pos1Isbelted": true,
        "row2Pos2Isbelted": true,
        "cabinTemp": 22,
        "cabinHumidity": 50,
        "tireConditionRow1Left": "Good",
        "tireConditionRow1Right": "Good",
        "tireConditionRow2Left": "Fair",
        "tireConditionRow2Right": "Good",
        "tirePressureRow1Left": "Normal",
        "tirePressureRow1Right": "Normal",
        "tirePressureRow2Left": "Low",
        "tirePressureRow2Right": "Normal",
        "brakePadWearRow1Left": "Good",
        "brakePadWearRow1Right": "Fair",
        "brakePadWearRow2Left": "Good",
        "brakePadWearRow2Right": "Good",
        "brakesWearRow1Right": "Good",
        "brakesWearRow1Left": "Good",
        "brakeWearRow2Left": "Good",
        "brakeWearRow2Right": "Good",
        "clutchWear": 0.2,
        "dashboardWarnning": null,
        "hasAirbagDeployed": false,
        "hasBrakesError": false,
        "engineWarning": null,
        "KnownVehicleDamage": null,
        "damagedParts": null,
        "damagedPartsCost": null,
        "upcomingService": "2024-03-15",
        "occupiedSeats": 4,
        "childSeatOccupiesSeat": 1,
        "consentGranted": true,
        "plateNumber": "ABC123",
        "registrationDate": "2022-01-15",
        "countryOfRegistration": "US",
        "chassisNumber": "XYZ789",
        "vin": "1HGCM82633A123456",
        "engineNumber": "ENG123",
        "vehicleWeight": 1500,
        "agencyRepair": false,
        "bodyType": "Sedan",
        "fuelType": "Gasoline",
        "aiClassification": "Level 2",
        "vehicleUse": true,
        "vehicleGarage": false,
        "vehicleBrand": "Toyota",
        "vehicleModel": "Camry",
        "seats": 5,
        "colour": "Silver",
        "sumInsured": 25000,
        "accessories": "Sunroof, GPS",
        "accessoryValue": "5000",
        "co2Emissions": false,
        "automaticTransmission": true,
        "lefthandDrive": false,
        "doors": 4,
        "securityDevice": true,
        "modification": false,
        "digitalKeyUsed": true,
        "blueBadgeAdapted": false,
        "distanceUnit": "Miles",
        "pleasureDistance": 10000,
        "businessDistance": 5000,
        "currentMileage": 18000,
        "yearlyMilage": 22000
    },
    {
        "id": 2,
        "HP": 180,
        "KW": 134.22,
        "torque": 220,
        "evHP": 120,
        "evKW": 89.48,
        "evTorque": 150,
        "acceleration": 8.2,
        "vehicleTopSpeed": 170,
        "engineCapacity": 1800,
        "modelYear": 2020,
        "hasTractionEnabled": true,
        "hasImmobilizer": true,
        "hasTheftDetection": true,
        "currentMileageDynamic": 25000,
        "yearlyMilageDynamic": 18000,
        "highwayYearlyMilageDynamic": 10000,
        "dailyMilageDynamic": 60,
        "serviceHistory": 3,
        "serviceDue": 28000,
        "timeToService": 600,
        "recallHistory": 0,
        "tractionControlEngaged": false,
        "accelerationLongitudinal": 0.9,
        "accelerationLateral": 0.3,
        "accelerationVertical": 0.2,
        "brakingFrequency": 350,
        "brakePedalForce": 130,
        "brakePedalSpeed": 0.6,
        "performanceMode": 2,
        "emergencyBraking": 0.4,
        "engnitionOn": true,
        "engnitionOff": false,
        "ignitionOnTime": 130,
        "ignitionOffTime": 35,
        "logitude": 40.7128,
        "latitude": -74.0060,
        "altitude": 100,
        "heading": 30,
        "isMoving": true,
        "hornIsActive": true,
        "drivingSpeed": 55,
        "wheelSpin": 0.6,
        "decelrationRate": 2.8,
        "steeringSpeedTurn": 0.15,
        "laneDepartureWarnning": 0.1,
        "adasAbsIsActive": false,
        "obstacleDetectionIsActive": true,
        "driverIntervention": true,
        "obstacleDetectionWarning": "Obstacle detected in front",
        "speedSet": 60,
        "yaw": 15,
        "pitch": 7,
        "roll": 0.7,
        "gForce": 0.9,
        "trailerIncluded": true,
        "row1Pos1Isbelted": false,
        "row1Pos2Isbelted": true,
        "row2Pos1Isbelted": false,
        "row2Pos2Isbelted": true,
        "cabinTemp": 20,
        "cabinHumidity": 45,
        "tireConditionRow1Left": "Good",
        "tireConditionRow1Right": "Fair",
        "tireConditionRow2Left": "Good",
        "tireConditionRow2Right": "Good",
        "tirePressureRow1Left": "Normal",
        "tirePressureRow1Right": "Low",
        "tirePressureRow2Left": "Normal",
        "tirePressureRow2Right": "Normal",
        "brakePadWearRow1Left": "Good",
        "brakePadWearRow1Right": "Good",
        "brakePadWearRow2Left": "Fair",
        "brakePadWearRow2Right": "Good",
        "brakesWearRow1Right": "Good",
        "brakesWearRow1Left": "Good",
        "brakeWearRow2Left": "Good",
        "brakeWearRow2Right": "Good",
        "clutchWear": 0.3,
        "dashboardWarnning": "Low fuel",
        "hasAirbagDeployed": false,
        "hasBrakesError": true,
        "engineWarning": "Check engine",
        "KnownVehicleDamage": "Scratch on the rear bumper",
        "damagedParts": "Rear bumper",
        "damagedPartsCost": 300,
        "upcomingService": "2024-04-10",
        "occupiedSeats": 2,
        "childSeatOccupiesSeat": 0,
        "consentGranted": true,
        "plateNumber": "XYZ456",
        "registrationDate": "2020-05-20",
        "countryOfRegistration": "CA",
        "chassisNumber": "ABC789",
        "vin": "2HGCM82633A654321",
        "engineNumber": "ENG456",
        "vehicleWeight": 1600,
        "agencyRepair": true,
        "bodyType": "SUV",
        "fuelType": "Diesel",
        "aiClassification": "Level 1",
        "vehicleUse": false,
        "vehicleGarage": true,
        "vehicleBrand": "Honda",
        "vehicleModel": "CR-V",
        "seats": 5,
        "colour": "Blue",
        "sumInsured": 30000,
        "accessories": "Roof rack, Tow hitch",
        "accessoryValue": "6000",
        "co2Emissions": true,
        "automaticTransmission": false,
        "lefthandDrive": true,
        "doors": 5,
        "securityDevice": true,
        "modification": true,
        "digitalKeyUsed": false,
        "blueBadgeAdapted": true,
        "distanceUnit": "Kilometers",
        "pleasureDistance": 12000,
        "businessDistance": 8000,
        "currentMileage": 21000,
        "yearlyMilage": 20000
    },
    {
        "id": 3,
        "HP": 220,
        "KW": 164.05,
        "torque": 270,
        "evHP": 150,
        "evKW": 111.85,
        "evTorque": 180,
        "acceleration": 6.8,
        "vehicleTopSpeed": 200,
        "engineCapacity": 2500,
        "modelYear": 2021,
        "hasTractionEnabled": true,
        "hasImmobilizer": true,
        "hasTheftDetection": true,
        "currentMileageDynamic": 18000,
        "yearlyMilageDynamic": 25000,
        "highwayYearlyMilageDynamic": 15000,
        "dailyMilageDynamic": 70,
        "serviceHistory": 1,
        "serviceDue": 32000,
        "timeToService": 400,
        "recallHistory": 2,
        "tractionControlEngaged": true,
        "accelerationLongitudinal": 1.0,
        "accelerationLateral": 0.4,
        "accelerationVertical": 0.3,
        "brakingFrequency": 320,
        "brakePedalForce": 140,
        "brakePedalSpeed": 0.7,
        "performanceMode": 3,
        "emergencyBraking": 0.5,
        "engnitionOn": true,
        "engnitionOff": false,
        "ignitionOnTime": 110,
        "ignitionOffTime": 25,
        "logitude": 41.8781,
        "latitude": -87.6298,
        "altitude": 200,
        "heading": 60,
        "isMoving": true,
        "hornIsActive": false,
        "drivingSpeed": 70,
        "wheelSpin": 0.4,
        "decelrationRate": 2.2,
        "steeringSpeedTurn": 0.2,
        "laneDepartureWarnning": 0.3,
        "adasAbsIsActive": true,
        "obstacleDetectionIsActive": false,
        "driverIntervention": false,
        "obstacleDetectionWarning": null,
        "speedSet": 75,
        "yaw": 20,
        "pitch": 10,
        "roll": 0.8,
        "gForce": 1.0,
        "trailerIncluded": true,
        "row1Pos1Isbelted": true,
        "row1Pos2Isbelted": false,
        "row2Pos1Isbelted": true,
        "row2Pos2Isbelted": true,
        "cabinTemp": 25,
        "cabinHumidity": 55,
        "tireConditionRow1Left": "Good",
        "tireConditionRow1Right": "Good",
        "tireConditionRow2Left": "Good",
        "tireConditionRow2Right": "Fair",
        "tirePressureRow1Left": "Normal",
        "tirePressureRow1Right": "Normal",
        "tirePressureRow2Left": "Normal",
        "tirePressureRow2Right": "Low",
        "brakePadWearRow1Left": "Good",
        "brakePadWearRow1Right": "Good",
        "brakePadWearRow2Left": "Good",
        "brakePadWearRow2Right": "Fair",
        "brakesWearRow1Right": "Good",
        "brakesWearRow1Left": "Good",
        "brakeWearRow2Left": "Good",
        "brakeWearRow2Right": "Good",
        "clutchWear": 0.1,
        "dashboardWarnning": "Low tire pressure",
        "hasAirbagDeployed": false,
        "hasBrakesError": false,
        "engineWarning": null,
        "KnownVehicleDamage": null,
        "damagedParts": null,
        "damagedPartsCost": null,
        "upcomingService": "2024-05-20",
        "occupiedSeats": 3,
        "childSeatOccupiesSeat": 1,
        "consentGranted": true,
        "plateNumber": "DEF789",
        "registrationDate": "2021-02-10",
        "countryOfRegistration": "UK",
        "chassisNumber": "LMN123",
        "vin": "3HGCM82633A987654",
        "engineNumber": "ENG789",
        "vehicleWeight": 1700,
        "agencyRepair": false,
        "bodyType": "Hatchback",
        "fuelType": "Electric",
        "aiClassification": "Level 3",
        "vehicleUse": true,
        "vehicleGarage": true,
        "vehicleBrand": "Tesla",
        "vehicleModel": "Model 3",
        "seats": 4,
        "colour": "Red",
        "sumInsured": 35000,
        "accessories": "Autopilot, Premium Sound System",
        "accessoryValue": "8000",
        "co2Emissions": false,
        "automaticTransmission": true,
        "lefthandDrive": false,
        "doors": 3,
        "securityDevice": true,
        "modification": false,
        "digitalKeyUsed": true,
        "blueBadgeAdapted": false,
        "distanceUnit": "Miles",
        "pleasureDistance": 15000,
        "businessDistance": 10000,
        "currentMileage": 19000,
        "yearlyMilage": 26000
    },
    {
        "id": 4,
        "HP": 240,
        "KW": 178.97,
        "torque": 290,
        "evHP": 180,
        "evKW": 134.22,
        "evTorque": 220,
        "acceleration": 6.0,
        "vehicleTopSpeed": 210,
        "engineCapacity": 2800,
        "modelYear": 2023,
        "hasTractionEnabled": true,
        "hasImmobilizer": true,
        "hasTheftDetection": false,
        "currentMileageDynamic": 20000,
        "yearlyMilageDynamic": 22000,
        "highwayYearlyMilageDynamic": 13000,
        "dailyMilageDynamic": 75,
        "serviceHistory": 2,
        "serviceDue": 30000,
        "timeToService": 500,
        "recallHistory": 1,
        "tractionControlEngaged": true,
        "accelerationLongitudinal": 1.2,
        "accelerationLateral": 0.5,
        "accelerationVertical": 0.4,
        "brakingFrequency": 380,
        "brakePedalForce": 150,
        "brakePedalSpeed": 0.8,
        "performanceMode": 3,
        "emergencyBraking": 0.6,
        "engnitionOn": true,
        "engnitionOff": false,
        "ignitionOnTime": 140,
        "ignitionOffTime": 40,
        "logitude": 37.7749,
        "latitude": -122.4194,
        "altitude": 180,
        "heading": 90,
        "isMoving": true,
        "hornIsActive": true,
        "drivingSpeed": 80,
        "wheelSpin": 0.3,
        "decelrationRate": 2.0,
        "steeringSpeedTurn": 0.3,
        "laneDepartureWarnning": 0.4,
        "adasAbsIsActive": false,
        "obstacleDetectionIsActive": true,
        "driverIntervention": true,
        "obstacleDetectionWarning": "Obstacle detected on the left",
        "speedSet": 85,
        "yaw": 25,
        "pitch": 12,
        "roll": 1.0,
        "gForce": 1.2,
        "trailerIncluded": false,
        "row1Pos1Isbelted": true,
        "row1Pos2Isbelted": false,
        "row2Pos1Isbelted": true,
        "row2Pos2Isbelted": true,
        "cabinTemp": 22,
        "cabinHumidity": 50,
        "tireConditionRow1Left": "Good",
        "tireConditionRow1Right": "Good",
        "tireConditionRow2Left": "Fair",
        "tireConditionRow2Right": "Good",
        "tirePressureRow1Left": "Normal",
        "tirePressureRow1Right": "Normal",
        "tirePressureRow2Left": "Low",
        "tirePressureRow2Right": "Normal",
        "brakePadWearRow1Left": "Good",
        "brakePadWearRow1Right": "Fair",
        "brakePadWearRow2Left": "Good",
        "brakePadWearRow2Right": "Good",
        "brakesWearRow1Right": "Good",
        "brakesWearRow1Left": "Good",
        "brakeWearRow2Left": "Good",
        "brakeWearRow2Right": "Good",
        "clutchWear": 0.4,
        "dashboardWarnning": null,
        "hasAirbagDeployed": false,
        "hasBrakesError": false,
        "engineWarning": null,
        "KnownVehicleDamage": "Minor scratch on the side",
        "damagedParts": "Side panel",
        "damagedPartsCost": 200,
        "upcomingService": "2024-06-25",
        "occupiedSeats": 5,
        "childSeatOccupiesSeat": 2,
        "consentGranted": true,
        "plateNumber": "GHI321",
        "registrationDate": "2023-03-05",
        "countryOfRegistration": "DE",
        "chassisNumber": "OPQ456",
        "vin": "4HGCM82633A246810",
        "engineNumber": "ENG123",
        "vehicleWeight": 1800,
        "agencyRepair": true,
        "bodyType": "Coupe",
        "fuelType": "Hybrid",
        "aiClassification": "Level 2",
        "vehicleUse": false,
        "vehicleGarage": true,
        "vehicleBrand": "BMW",
        "vehicleModel": "M4",
        "seats": 4,
        "colour": "Black",
        "sumInsured": 40000,
        "accessories": "M Performance Exhaust",
        "accessoryValue": "12000",
        "co2Emissions": true,
        "automaticTransmission": true,
        "lefthandDrive": true,
        "doors": 2,
        "securityDevice": true,
        "modification": true,
        "digitalKeyUsed": false,
        "blueBadgeAdapted": true,
        "distanceUnit": "Kilometers",
        "pleasureDistance": 18000,
        "businessDistance": 12000,
        "currentMileage": 22000,
        "yearlyMilage": 24000
    },
    {
        "id": 5,
        "HP": 190,
        "KW": 141.68,
        "torque": 240,
        "evHP": 130,
        "evKW": 97.04,
        "evTorque": 160,
        "acceleration": 7.0,
        "vehicleTopSpeed": 190,
        "engineCapacity": 2100,
        "modelYear": 2022,
        "hasTractionEnabled": true,
        "hasImmobilizer": true,
        "hasTheftDetection": true,
        "currentMileageDynamic": 21000,
        "yearlyMilageDynamic": 20000,
        "highwayYearlyMilageDynamic": 11000,
        "dailyMilageDynamic": 65,
        "serviceHistory": 1,
        "serviceDue": 28000,
        "timeToService": 450,
        "recallHistory": 0,
        "tractionControlEngaged": false,
        "accelerationLongitudinal": 0.8,
        "accelerationLateral": 0.2,
        "accelerationVertical": 0.1,
        "brakingFrequency": 320,
        "brakePedalForce": 130,
        "brakePedalSpeed": 0.6,
        "performanceMode": 2,
        "emergencyBraking": 0.3,
        "engnitionOn": true,
        "engnitionOff": false,
        "ignitionOnTime": 120,
        "ignitionOffTime": 30,
        "logitude": 51.5099,
        "latitude": -0.1180,
        "altitude": 30,
        "heading": 120,
        "isMoving": true,
        "hornIsActive": true,
        "drivingSpeed": 75,
        "wheelSpin": 0.5,
        "decelrationRate": 2.5,
        "steeringSpeedTurn": 0.1,
        "laneDepartureWarnning": 0.2,
        "adasAbsIsActive": true,
        "obstacleDetectionIsActive": false,
        "driverIntervention": false,
        "obstacleDetectionWarning": null,
        "speedSet": 80,
        "yaw": 15,
        "pitch": 7,
        "roll": 0.7,
        "gForce": 0.9,
        "trailerIncluded": false,
        "row1Pos1Isbelted": false,
        "row1Pos2Isbelted": true,
        "row2Pos1Isbelted": false,
        "row2Pos2Isbelted": true,
        "cabinTemp": 22,
        "cabinHumidity": 50,
        "tireConditionRow1Left": "Good",
        "tireConditionRow1Right": "Good",
        "tireConditionRow2Left": "Good",
        "tireConditionRow2Right": "Fair",
        "tirePressureRow1Left": "Normal",
        "tirePressureRow1Right": "Low",
        "tirePressureRow2Left": "Normal",
        "tirePressureRow2Right": "Normal",
        "brakePadWearRow1Left": "Good",
        "brakePadWearRow1Right": "Good",
        "brakePadWearRow2Left": "Fair",
        "brakePadWearRow2Right": "Good",
        "brakesWearRow1Right": "Good",
        "brakesWearRow1Left": "Good",
        "brakeWearRow2Left": "Good",
        "brakeWearRow2Right": "Good",
        "clutchWear": 0.3,
        "dashboardWarnning": "Low fuel",
        "hasAirbagDeployed": false,
        "hasBrakesError": true,
        "engineWarning": "Check engine",
        "KnownVehicleDamage": "Minor scratch on the front bumper",
        "damagedParts": "Front bumper",
        "damagedPartsCost": 150,
        "upcomingService": "2024-07-15",
        "occupiedSeats": 2,
        "childSeatOccupiesSeat": 0,
        "consentGranted": true,
        "plateNumber": "JKL987",
        "registrationDate": "2022-04-18",
        "countryOfRegistration": "FR",
        "chassisNumber": "QRS789",
        "vin": "5HGCM82633A135790",
        "engineNumber": "ENG456",
        "vehicleWeight": 1600,
        "agencyRepair": false,
        "bodyType": "Sedan",
        "fuelType": "Gasoline",
        "aiClassification": "Level 1",
        "vehicleUse": true,
        "vehicleGarage": false,
        "vehicleBrand": "Mercedes-Benz",
        "vehicleModel": "C-Class",
        "seats": 5,
        "colour": "White",
        "sumInsured": 30000,
        "accessories": "Panoramic sunroof, Navigation system",
        "accessoryValue": "5000",
        "co2Emissions": true,
        "automaticTransmission": true,
        "lefthandDrive": false,
        "doors": 4,
        "securityDevice": true,
        "modification": false,
        "digitalKeyUsed": true,
        "blueBadgeAdapted": false,
        "distanceUnit": "Miles",
        "pleasureDistance": 12000,
        "businessDistance": 8000,
        "currentMileage": 19000,
        "yearlyMilage": 22000
    }
]